MetaHeuristicsFS.py
MetaHeuristicsFS-0.0.8.dist-info/LICENSE
MetaHeuristicsFS-0.0.8.dist-info/METADATA
MetaHeuristicsFS-0.0.8.dist-info/WHEEL
MetaHeuristicsFS-0.0.8.dist-info/top_level.txt
MetaHeuristicsFS-0.0.8.dist-info/RECORD
