Metadata-Version: 2.1
Name: MetaHeuristicsFS
Version: 0.0.8
Summary: Implementation of metaheuristic algorithms for machine learning feature selection. Companion library for the book `Feature Engineering & Selection for Explainable Models: A Second Course for Data Scientists`
Home-page: https://github.com/StatguyUser/MetaHeuristicsFS
Author: StatguyUser
License: UNKNOWN
Download-URL: https://github.com/MetaHeuristicsFS/MetaHeuristicsFS.git
Platform: UNKNOWN
Requires-Dist: numpy
Requires-Dist: scikit-learn
Requires-Dist: pandas
